spryngtime_analytics_sdk/__init__.py
spryngtime_analytics_sdk/api_client.py
spryngtime_analytics_sdk/api_response.py
spryngtime_analytics_sdk/apis/__init__.py
spryngtime_analytics_sdk/apis/path_to_api.py
spryngtime_analytics_sdk/apis/paths/__init__.py
spryngtime_analytics_sdk/apis/paths/root.py
spryngtime_analytics_sdk/apis/paths/track_usage.py
spryngtime_analytics_sdk/apis/paths/users.py
spryngtime_analytics_sdk/apis/tag_to_api.py
spryngtime_analytics_sdk/apis/tags/__init__.py
spryngtime_analytics_sdk/apis/tags/default_api.py
spryngtime_analytics_sdk/apis/tags/default_api_raw.py
spryngtime_analytics_sdk/apis/tags/usage_tracking_api.py
spryngtime_analytics_sdk/apis/tags/usage_tracking_api_raw.py
spryngtime_analytics_sdk/client.py
spryngtime_analytics_sdk/client.pyi
spryngtime_analytics_sdk/client_custom.py
spryngtime_analytics_sdk/configuration.py
spryngtime_analytics_sdk/exceptions.py
spryngtime_analytics_sdk/exceptions_base.py
spryngtime_analytics_sdk/model/__init__.py
spryngtime_analytics_sdk/model/choice.py
spryngtime_analytics_sdk/model/choice.pyi
spryngtime_analytics_sdk/model/message.py
spryngtime_analytics_sdk/model/message.pyi
spryngtime_analytics_sdk/model/open_ai_response.py
spryngtime_analytics_sdk/model/open_ai_response.pyi
spryngtime_analytics_sdk/model/track_usage_request.py
spryngtime_analytics_sdk/model/track_usage_request.pyi
spryngtime_analytics_sdk/model/usage_detail.py
spryngtime_analytics_sdk/model/usage_detail.pyi
spryngtime_analytics_sdk/models/__init__.py
spryngtime_analytics_sdk/paths/__init__.py
spryngtime_analytics_sdk/paths/root/__init__.py
spryngtime_analytics_sdk/paths/root/get.py
spryngtime_analytics_sdk/paths/root/get.pyi
spryngtime_analytics_sdk/paths/track_usage/__init__.py
spryngtime_analytics_sdk/paths/track_usage/post.py
spryngtime_analytics_sdk/paths/track_usage/post.pyi
spryngtime_analytics_sdk/paths/users/__init__.py
spryngtime_analytics_sdk/paths/users/post.py
spryngtime_analytics_sdk/paths/users/post.pyi
spryngtime_analytics_sdk_python_sdk-1.0.1.dist-info/LICENSE
spryngtime_analytics_sdk_python_sdk-1.0.1.dist-info/METADATA
spryngtime_analytics_sdk_python_sdk-1.0.1.dist-info/WHEEL
spryngtime_analytics_sdk_python_sdk-1.0.1.dist-info/RECORD
